scaleway_qaas_client/__init__.py
scaleway_qaas_client/versions.py
scaleway_qaas_client/v1alpha1/__init__.py
scaleway_qaas_client/v1alpha1/client.py
scaleway_qaas_client/v1alpha1/job_payload/__init__.py
scaleway_qaas_client/v1alpha1/job_payload/models.py
scaleway_qaas_client/v1alpha1/quantum_as_a_service_api_client/__init__.py
scaleway_qaas_client/v1alpha1/quantum_as_a_service_api_client/client.py
scaleway_qaas_client/v1alpha1/quantum_as_a_service_api_client/errors.py
scaleway_qaas_client/v1alpha1/quantum_as_a_service_api_client/py.typed
scaleway_qaas_client/v1alpha1/quantum_as_a_service_api_client/types.py
scaleway_qaas_client/v1alpha1/quantum_as_a_service_api_client/api/__init__.py
scaleway_qaas_client/v1alpha1/quantum_as_a_service_api_client/api/applications/__init__.py
scaleway_qaas_client/v1alpha1/quantum_as_a_service_api_client/api/applications/get_application.py
scaleway_qaas_client/v1alpha1/quantum_as_a_service_api_client/api/applications/list_applications.py
scaleway_qaas_client/v1alpha1/quantum_as_a_service_api_client/api/bookings/__init__.py
scaleway_qaas_client/v1alpha1/quantum_as_a_service_api_client/api/bookings/get_booking.py
scaleway_qaas_client/v1alpha1/quantum_as_a_service_api_client/api/bookings/list_bookings.py
scaleway_qaas_client/v1alpha1/quantum_as_a_service_api_client/api/bookings/update_booking.py
scaleway_qaas_client/v1alpha1/quantum_as_a_service_api_client/api/default/__init__.py
scaleway_qaas_client/v1alpha1/quantum_as_a_service_api_client/api/default/list_session_ac_ls.py
scaleway_qaas_client/v1alpha1/quantum_as_a_service_api_client/api/jobs/__init__.py
scaleway_qaas_client/v1alpha1/quantum_as_a_service_api_client/api/jobs/cancel_job.py
scaleway_qaas_client/v1alpha1/quantum_as_a_service_api_client/api/jobs/create_job.py
scaleway_qaas_client/v1alpha1/quantum_as_a_service_api_client/api/jobs/delete_job.py
scaleway_qaas_client/v1alpha1/quantum_as_a_service_api_client/api/jobs/get_job.py
scaleway_qaas_client-0.1.24.dist-info/licenses/LICENSE
scaleway_qaas_client-0.1.24.dist-info/METADATA
scaleway_qaas_client-0.1.24.dist-info/WHEEL
scaleway_qaas_client-0.1.24.dist-info/top_level.txt
scaleway_qaas_client-0.1.24.dist-info/RECORD
