Metadata-Version: 2.4
Name: scaleway_qaas_client
Version: 0.1.24
Summary: ('Python client providing primitives to be used from other quantum SDKs',)
Author: The Scaleway Developers
Author-email: vmacheret@scaleway.com
License: Apache 2
Project-URL: Documentation, https://www.scaleway.com/en/quantum-as-a-service/
Project-URL: Source, https://github.com/scaleway/scaleway-qaas-client-pythom
Project-URL: Tracker, https://github.com/scaleway/scaleway-qaas-client-pythom/issues
Requires-Python: >=3.12.0
License-File: LICENSE
Requires-Dist: dataclasses-json>=0.6.4
Requires-Dist: dataclasses>=0.6
Requires-Dist: randomname>=0.2.1
Requires-Dist: httpx>=0.27.0
Requires-Dist: pytimeparse>=1.1.8
Requires-Dist: attrs>=22.2.0
Requires-Dist: python-dateutil>=2.8.0
Dynamic: author
Dynamic: author-email
Dynamic: description
Dynamic: description-content-type
Dynamic: license
Dynamic: license-file
Dynamic: project-url
Dynamic: requires-dist
Dynamic: requires-python
Dynamic: summary
